<?xml version="1.0" encoding="utf-8"?>
<Return>
  <ReturnHeader binaryAttachmentCnt="0">
    <ReturnTs>2019-01-11T10:58:16-08:00</ReturnTs>
    <TaxPeriodEndDt>2018-05-31</TaxPeriodEndDt>
    <PreparerFirmGrp>
      <PreparerFirmEIN>133133377</PreparerFirmEIN>
      <PreparerFirmName>
        <BusinessNameLine1Txt>Bilotta &amp; Santoli CPAs PC</BusinessNameLine1Txt>
      </PreparerFirmName>
      <PreparerUSAddress>
        <AddressLine1Txt>185 Halstead Avenue</AddressLine1Txt>
        <CityNm>Harrison</CityNm>
        <StateAbbreviationCd>NY</StateAbbreviationCd>
        <ZIPCd>10528</ZIPCd>
      </PreparerUSAddress>
    </PreparerFirmGrp>
    <ReturnTypeCd>990</ReturnTypeCd>
    <TaxPeriodBeginDt>2017-06-01</TaxPeriodBeginDt>
    <Filer>
      <EIN>030591547</EIN>
      <BusinessName>
        <BusinessNameLine1Txt>HARRISON YOUTH SOCCER CLUB INC</BusinessNameLine1Txt>
      </BusinessName>
      <BusinessNameControlTxt>HARR</BusinessNameControlTxt>
      <PhoneNum>9148790240</PhoneNum>
      <USAddress>
        <AddressLine1Txt>PO Box 732</AddressLine1Txt>
        <CityNm>Harrison</CityNm>
        <StateAbbreviationCd>NY</StateAbbreviationCd>
        <ZIPCd>10528</ZIPCd>
      </USAddress>
    </Filer>
    <BusinessOfficerGrp>
      <PersonNm>Grace Malota</PersonNm>
      <PersonTitleTxt>Treasurer</PersonTitleTxt>
      <SignatureDt>2019-01-11</SignatureDt>
      <DiscussWithPaidPreparerInd>true</DiscussWithPaidPreparerInd>
    </BusinessOfficerGrp>
    <PreparerPersonGrp>
      <PreparerPersonNm>LORENZO SANTOLI CPA</PreparerPersonNm>
      <PTIN>P00127987</PTIN>
      <PhoneNum>9148354542</PhoneNum>
    </PreparerPersonGrp>
    <TaxYr>2017</TaxYr>
    <BuildTS>2019-02-21 02:37:17Z</BuildTS>
  </ReturnHeader>
  <ReturnData documentCnt="5">
    <IRS990 documentId="IRS990" referenceDocumentId="IRS990ScheduleO 990BinaryAttachments.1" softwareId="17005038" softwareVersionNum="2017v2.2">
      <GrossReceiptsAmt>338909</GrossReceiptsAmt>
      <GroupReturnForAffiliatesInd>false</GroupReturnForAffiliatesInd>
      <AllAffiliatesIncludedInd>false</AllAffiliatesIncludedInd>
      <Organization501c3Ind>X</Organization501c3Ind>
      <WebsiteAddressTxt>WWW.HARRISONTRAVELSOCCER.ORG</WebsiteAddressTxt>
      <TypeOfOrganizationCorpInd>X</TypeOfOrganizationCorpInd>
      <FormationYr>2006</FormationYr>
      <LegalDomicileStateCd>NY</LegalDomicileStateCd>
      <ActivityOrMissionDesc>THE GROWTH AND PROMOTION OF THE GAME OF SOCCER WITHIN THE TOWN AND VILLAGE OF HARRISON, NY</ActivityOrMissionDesc>
      <VotingMembersGoverningBodyCnt>4</VotingMembersGoverningBodyCnt>
      <VotingMembersIndependentCnt>0</VotingMembersIndependentCnt>
      <TotalEmployeeCnt>0</TotalEmployeeCnt>
      <TotalGrossUBIAmt>0</TotalGrossUBIAmt>
      <CYContributionsGrantsAmt>0</CYContributionsGrantsAmt>
      <PYProgramServiceRevenueAmt>310792</PYProgramServiceRevenueAmt>
      <CYProgramServiceRevenueAmt>316643</CYProgramServiceRevenueAmt>
      <PYInvestmentIncomeAmt>145</PYInvestmentIncomeAmt>
      <CYInvestmentIncomeAmt>130</CYInvestmentIncomeAmt>
      <CYOtherRevenueAmt>22136</CYOtherRevenueAmt>
      <PYTotalRevenueAmt>310937</PYTotalRevenueAmt>
      <CYTotalRevenueAmt>338909</CYTotalRevenueAmt>
      <CYGrantsAndSimilarPaidAmt>17000</CYGrantsAndSimilarPaidAmt>
      <CYBenefitsPaidToMembersAmt>0</CYBenefitsPaidToMembersAmt>
      <CYSalariesCompEmpBnftPaidAmt>0</CYSalariesCompEmpBnftPaidAmt>
      <CYTotalProfFndrsngExpnsAmt>0</CYTotalProfFndrsngExpnsAmt>
      <CYTotalFundraisingExpenseAmt>0</CYTotalFundraisingExpenseAmt>
      <PYOtherExpensesAmt>348185</PYOtherExpensesAmt>
      <CYOtherExpensesAmt>397709</CYOtherExpensesAmt>
      <PYTotalExpensesAmt>348185</PYTotalExpensesAmt>
      <CYTotalExpensesAmt>414709</CYTotalExpensesAmt>
      <PYRevenuesLessExpensesAmt>-37248</PYRevenuesLessExpensesAmt>
      <CYRevenuesLessExpensesAmt>-75800</CYRevenuesLessExpensesAmt>
      <TotalAssetsBOYAmt>244274</TotalAssetsBOYAmt>
      <TotalAssetsEOYAmt>168474</TotalAssetsEOYAmt>
      <TotalLiabilitiesEOYAmt>0</TotalLiabilitiesEOYAmt>
      <NetAssetsOrFundBalancesBOYAmt>244274</NetAssetsOrFundBalancesBOYAmt>
      <NetAssetsOrFundBalancesEOYAmt>168474</NetAssetsOrFundBalancesEOYAmt>
      <MissionDesc>THE GROWTH AND PROMOTION OF THE GAME OF SOCCER WITHIN THE TOWN AND VILLAGE OF HARRISON, NY</MissionDesc>
      <SignificantNewProgramSrvcInd>false</SignificantNewProgramSrvcInd>
      <SignificantChangeInd>false</SignificantChangeInd>
      <ExpenseAmt>392577</ExpenseAmt>
      <Desc>THE CLUB PROMOTES THE GAME OF SOCCER AND TEACHES AND TRAINS PLAYERS,COACHES, REFEREES AND ADMINISTRATORS. IT ALSO PROMOTES GOOD SPORTSMANSHIP AND DEVELOPS LEADERSHIP QUALITIES AMONG PLAYERS, COACHES, PARENTS AND SPECTATORS. IN ADDITION THE CLUB HELPS TO DEVELOP PHYSICAL FITNESS AND MENTAL ALERTNESS AND PROVIDES AN ENJOYABLE RECREATIONAL ACTIVITY</Desc>
      <TotalProgramServiceExpensesAmt>392577</TotalProgramServiceExpensesAmt>
      <DescribedInSection501c3Ind referenceDocumentId="IRS990ScheduleA">true</DescribedInSection501c3Ind>
      <ScheduleBRequiredInd>false</ScheduleBRequiredInd>
      <PoliticalCampaignActyInd>false</PoliticalCampaignActyInd>
      <LobbyingActivitiesInd>false</LobbyingActivitiesInd>
      <SubjectToProxyTaxInd>false</SubjectToProxyTaxInd>
      <DonorAdvisedFundInd referenceDocumentId="IRS990ScheduleD">false</DonorAdvisedFundInd>
      <ConservationEasementsInd referenceDocumentId="IRS990ScheduleD">false</ConservationEasementsInd>
      <CollectionsOfArtInd referenceDocumentId="IRS990ScheduleD">false</CollectionsOfArtInd>
      <CreditCounselingInd referenceDocumentId="IRS990ScheduleD">false</CreditCounselingInd>
      <TempOrPermanentEndowmentsInd referenceDocumentId="IRS990ScheduleD">false</TempOrPermanentEndowmentsInd>
      <ReportLandBuildingEquipmentInd referenceDocumentId="IRS990ScheduleD">true</ReportLandBuildingEquipmentInd>
      <ReportInvestmentsOtherSecInd referenceDocumentId="IRS990ScheduleD">false</ReportInvestmentsOtherSecInd>
      <ReportProgramRelatedInvstInd referenceDocumentId="IRS990ScheduleD">false</ReportProgramRelatedInvstInd>
      <ReportOtherAssetsInd referenceDocumentId="IRS990ScheduleD">false</ReportOtherAssetsInd>
      <ReportOtherLiabilitiesInd referenceDocumentId="IRS990ScheduleD">false</ReportOtherLiabilitiesInd>
      <IncludeFIN48FootnoteInd referenceDocumentId="IRS990ScheduleD">false</IncludeFIN48FootnoteInd>
      <IndependentAuditFinclStmtInd referenceDocumentId="IRS990ScheduleD">false</IndependentAuditFinclStmtInd>
      <ConsolidatedAuditFinclStmtInd referenceDocumentId="IRS990ScheduleD">false</ConsolidatedAuditFinclStmtInd>
      <SchoolOperatingInd>false</SchoolOperatingInd>
      <ForeignOfficeInd>false</ForeignOfficeInd>
      <ForeignActivitiesInd>false</ForeignActivitiesInd>
      <MoreThan5000KToOrgInd>false</MoreThan5000KToOrgInd>
      <MoreThan5000KToIndividualsInd>false</MoreThan5000KToIndividualsInd>
      <ProfessionalFundraisingInd>false</ProfessionalFundraisingInd>
      <FundraisingActivitiesInd>false</FundraisingActivitiesInd>
      <GamingActivitiesInd>false</GamingActivitiesInd>
      <OperateHospitalInd>false</OperateHospitalInd>
      <GrantsToOrganizationsInd referenceDocumentId="IRS990ScheduleI">true</GrantsToOrganizationsInd>
      <GrantsToIndividualsInd referenceDocumentId="IRS990ScheduleI">false</GrantsToIndividualsInd>
      <ScheduleJRequiredInd>false</ScheduleJRequiredInd>
      <TaxExemptBondsInd>false</TaxExemptBondsInd>
      <InvestTaxExemptBondsInd>false</InvestTaxExemptBondsInd>
      <EscrowAccountInd>false</EscrowAccountInd>
      <OnBehalfOfIssuerInd>false</OnBehalfOfIssuerInd>
      <EngagedInExcessBenefitTransInd>false</EngagedInExcessBenefitTransInd>
      <PYExcessBenefitTransInd>false</PYExcessBenefitTransInd>
      <LoanOutstandingInd>false</LoanOutstandingInd>
      <GrantToRelatedPersonInd>false</GrantToRelatedPersonInd>
      <BusinessRlnWithOrgMemInd>false</BusinessRlnWithOrgMemInd>
      <BusinessRlnWithFamMemInd>false</BusinessRlnWithFamMemInd>
      <BusinessRlnWithOfficerEntInd>false</BusinessRlnWithOfficerEntInd>
      <DeductibleNonCashContriInd>false</DeductibleNonCashContriInd>
      <DeductibleArtContributionInd>false</DeductibleArtContributionInd>
      <TerminateOperationsInd>false</TerminateOperationsInd>
      <PartialLiquidationInd>false</PartialLiquidationInd>
      <DisregardedEntityInd>false</DisregardedEntityInd>
      <RelatedEntityInd>false</RelatedEntityInd>
      <RelatedOrganizationCtrlEntInd>false</RelatedOrganizationCtrlEntInd>
      <TrnsfrExmptNonChrtblRltdOrgInd>false</TrnsfrExmptNonChrtblRltdOrgInd>
      <ActivitiesConductedPrtshpInd>false</ActivitiesConductedPrtshpInd>
      <ScheduleORequiredInd>false</ScheduleORequiredInd>
      <IRPDocumentCnt>0</IRPDocumentCnt>
      <IRPDocumentW2GCnt>0</IRPDocumentW2GCnt>
      <BackupWthldComplianceInd>false</BackupWthldComplianceInd>
      <EmployeeCnt>0</EmployeeCnt>
      <EmploymentTaxReturnsFiledInd>false</EmploymentTaxReturnsFiledInd>
      <UnrelatedBusIncmOverLimitInd>false</UnrelatedBusIncmOverLimitInd>
      <Form990TFiledInd>false</Form990TFiledInd>
      <ForeignFinancialAccountInd>false</ForeignFinancialAccountInd>
      <ProhibitedTaxShelterTransInd>false</ProhibitedTaxShelterTransInd>
      <TaxablePartyNotificationInd>false</TaxablePartyNotificationInd>
      <NondeductibleContributionsInd>false</NondeductibleContributionsInd>
      <QuidProQuoContributionsInd>false</QuidProQuoContributionsInd>
      <Form8282PropertyDisposedOfInd>false</Form8282PropertyDisposedOfInd>
      <Form8282FiledCnt>0</Form8282FiledCnt>
      <RcvFndsToPayPrsnlBnftCntrctInd>false</RcvFndsToPayPrsnlBnftCntrctInd>
      <PayPremiumsPrsnlBnftCntrctInd>false</PayPremiumsPrsnlBnftCntrctInd>
      <Form8899Filedind>false</Form8899Filedind>
      <Form1098CFiledInd>false</Form1098CFiledInd>
      <DAFExcessBusinessHoldingsInd>false</DAFExcessBusinessHoldingsInd>
      <TaxableDistributionsInd>false</TaxableDistributionsInd>
      <DistributionToDonorInd>false</DistributionToDonorInd>
      <OrgFiledInLieuOfForm1041Ind>false</OrgFiledInLieuOfForm1041Ind>
      <LicensedMoreThanOneStateInd>false</LicensedMoreThanOneStateInd>
      <IndoorTanningServicesInd>false</IndoorTanningServicesInd>
      <InfoInScheduleOPartVIInd>X</InfoInScheduleOPartVIInd>
      <GoverningBodyVotingMembersCnt>4</GoverningBodyVotingMembersCnt>
      <IndependentVotingMemberCnt>0</IndependentVotingMemberCnt>
      <FamilyOrBusinessRlnInd>false</FamilyOrBusinessRlnInd>
      <DelegationOfMgmtDutiesInd>false</DelegationOfMgmtDutiesInd>
      <ChangeToOrgDocumentsInd>false</ChangeToOrgDocumentsInd>
      <MaterialDiversionOrMisuseInd>false</MaterialDiversionOrMisuseInd>
      <MembersOrStockholdersInd>false</MembersOrStockholdersInd>
      <ElectionOfBoardMembersInd>false</ElectionOfBoardMembersInd>
      <DecisionsSubjectToApprovaInd>false</DecisionsSubjectToApprovaInd>
      <MinutesOfGoverningBodyInd>false</MinutesOfGoverningBodyInd>
      <MinutesOfCommitteesInd>false</MinutesOfCommitteesInd>
      <OfficerMailingAddressInd>false</OfficerMailingAddressInd>
      <LocalChaptersInd>false</LocalChaptersInd>
      <Form990ProvidedToGvrnBodyInd>false</Form990ProvidedToGvrnBodyInd>
      <ConflictOfInterestPolicyInd>false</ConflictOfInterestPolicyInd>
      <AnnualDisclosureCoveredPrsnInd>false</AnnualDisclosureCoveredPrsnInd>
      <RegularMonitoringEnfrcInd>false</RegularMonitoringEnfrcInd>
      <WhistleblowerPolicyInd>false</WhistleblowerPolicyInd>
      <DocumentRetentionPolicyInd>false</DocumentRetentionPolicyInd>
      <CompensationProcessCEOInd>false</CompensationProcessCEOInd>
      <CompensationProcessOtherInd>false</CompensationProcessOtherInd>
      <InvestmentInJointVentureInd>false</InvestmentInJointVentureInd>
      <BooksInCareOfDetail>
        <PersonNm>GRACE MALOTA</PersonNm>
        <PhoneNum>9148790240</PhoneNum>
        <USAddress>
          <AddressLine1Txt>1 Canterbury Rd N</AddressLine1Txt>
          <CityNm>HARRISON</CityNm>
          <StateAbbreviationCd>NY</StateAbbreviationCd>
          <ZIPCd>10528</ZIPCd>
        </USAddress>
      </BooksInCareOfDetail>
      <NoListedPersonsCompensatedInd>X</NoListedPersonsCompensatedInd>
      <Form990PartVIISectionAGrp>
        <PersonNm>Daniel Gartner</PersonNm>
        <TitleTxt>President</TitleTxt>
        <AverageHoursPerWeekRt>0.00</AverageHoursPerWeekRt>
        <AverageHoursPerWeekRltdOrgRt>0.00</AverageHoursPerWeekRltdOrgRt>
        <IndividualTrusteeOrDirectorInd>X</IndividualTrusteeOrDirectorInd>
        <ReportableCompFromOrgAmt>0</ReportableCompFromOrgAmt>
        <ReportableCompFromRltdOrgAmt>0</ReportableCompFromRltdOrgAmt>
        <OtherCompensationAmt>0</OtherCompensationAmt>
      </Form990PartVIISectionAGrp>
      <Form990PartVIISectionAGrp>
        <PersonNm>Lisa Nero</PersonNm>
        <TitleTxt>Secretary</TitleTxt>
        <AverageHoursPerWeekRt>0.00</AverageHoursPerWeekRt>
        <AverageHoursPerWeekRltdOrgRt>0.00</AverageHoursPerWeekRltdOrgRt>
        <IndividualTrusteeOrDirectorInd>X</IndividualTrusteeOrDirectorInd>
        <ReportableCompFromOrgAmt>0</ReportableCompFromOrgAmt>
        <ReportableCompFromRltdOrgAmt>0</ReportableCompFromRltdOrgAmt>
        <OtherCompensationAmt>0</OtherCompensationAmt>
      </Form990PartVIISectionAGrp>
      <Form990PartVIISectionAGrp>
        <PersonNm>Grace Malota</PersonNm>
        <TitleTxt>Treasurer</TitleTxt>
        <AverageHoursPerWeekRt>0.00</AverageHoursPerWeekRt>
        <AverageHoursPerWeekRltdOrgRt>0.00</AverageHoursPerWeekRltdOrgRt>
        <IndividualTrusteeOrDirectorInd>X</IndividualTrusteeOrDirectorInd>
        <ReportableCompFromOrgAmt>0</ReportableCompFromOrgAmt>
        <ReportableCompFromRltdOrgAmt>0</ReportableCompFromRltdOrgAmt>
        <OtherCompensationAmt>0</OtherCompensationAmt>
      </Form990PartVIISectionAGrp>
      <Form990PartVIISectionAGrp>
        <PersonNm>Joseph Stilo</PersonNm>
        <TitleTxt>Vice President</TitleTxt>
        <AverageHoursPerWeekRt>0.00</AverageHoursPerWeekRt>
        <AverageHoursPerWeekRltdOrgRt>0.00</AverageHoursPerWeekRltdOrgRt>
        <IndividualTrusteeOrDirectorInd>X</IndividualTrusteeOrDirectorInd>
        <ReportableCompFromOrgAmt>0</ReportableCompFromOrgAmt>
        <ReportableCompFromRltdOrgAmt>0</ReportableCompFromRltdOrgAmt>
        <OtherCompensationAmt>0</OtherCompensationAmt>
      </Form990PartVIISectionAGrp>
      <IndivRcvdGreaterThan100KCnt>0</IndivRcvdGreaterThan100KCnt>
      <FormerOfcrEmployeesListedInd>false</FormerOfcrEmployeesListedInd>
      <TotalCompGreaterThan150KInd>false</TotalCompGreaterThan150KInd>
      <CompensationFromOtherSrcsInd>false</CompensationFromOtherSrcsInd>
      <CntrctRcvdGreaterThan100KCnt>0</CntrctRcvdGreaterThan100KCnt>
      <TotalContributionsAmt>0</TotalContributionsAmt>
      <ProgramServiceRevenueGrp>
        <Desc>Membership Dues &amp; Assessments</Desc>
        <TotalRevenueColumnAmt>316643</TotalRevenueColumnAmt>
        <RelatedOrExemptFuncIncomeAmt>316643</RelatedOrExemptFuncIncomeAmt>
      </ProgramServiceRevenueGrp>
      <TotalProgramServiceRevenueAmt>316643</TotalProgramServiceRevenueAmt>
      <InvestmentIncomeGrp>
        <TotalRevenueColumnAmt>130</TotalRevenueColumnAmt>
        <RelatedOrExemptFuncIncomeAmt>130</RelatedOrExemptFuncIncomeAmt>
      </InvestmentIncomeGrp>
      <IncmFromInvestBondProceedsGrp>
        <TotalRevenueColumnAmt>0</TotalRevenueColumnAmt>
      </IncmFromInvestBondProceedsGrp>
      <RoyaltiesRevenueGrp>
        <TotalRevenueColumnAmt>0</TotalRevenueColumnAmt>
      </RoyaltiesRevenueGrp>
      <NetRentalIncomeOrLossGrp>
        <TotalRevenueColumnAmt>0</TotalRevenueColumnAmt>
      </NetRentalIncomeOrLossGrp>
      <NetGainOrLossInvestmentsGrp>
        <TotalRevenueColumnAmt>0</TotalRevenueColumnAmt>
      </NetGainOrLossInvestmentsGrp>
      <NetIncmFromFundraisingEvtGrp>
        <TotalRevenueColumnAmt>0</TotalRevenueColumnAmt>
      </NetIncmFromFundraisingEvtGrp>
      <NetIncomeFromGamingGrp>
        <TotalRevenueColumnAmt>0</TotalRevenueColumnAmt>
      </NetIncomeFromGamingGrp>
      <NetIncomeOrLossGrp>
        <TotalRevenueColumnAmt>0</TotalRevenueColumnAmt>
      </NetIncomeOrLossGrp>
      <OtherRevenueTotalAmt>22136</OtherRevenueTotalAmt>
      <TotalRevenueGrp>
        <TotalRevenueColumnAmt>338909</TotalRevenueColumnAmt>
        <RelatedOrExemptFuncIncomeAmt>338909</RelatedOrExemptFuncIncomeAmt>
      </TotalRevenueGrp>
      <InfoInScheduleOPartIXInd>X</InfoInScheduleOPartIXInd>
      <GrantsToDomesticOrgsGrp>
        <TotalAmt>17000</TotalAmt>
        <ProgramServicesAmt>17000</ProgramServicesAmt>
      </GrantsToDomesticOrgsGrp>
      <GrantsToDomesticIndividualsGrp>
        <TotalAmt>0</TotalAmt>
      </GrantsToDomesticIndividualsGrp>
      <ForeignGrantsGrp>
        <TotalAmt>0</TotalAmt>
      </ForeignGrantsGrp>
      <BenefitsToMembersGrp>
        <TotalAmt>0</TotalAmt>
      </BenefitsToMembersGrp>
      <CompCurrentOfcrDirectorsGrp>
        <TotalAmt>0</TotalAmt>
      </CompCurrentOfcrDirectorsGrp>
      <CompDisqualPersonsGrp>
        <TotalAmt>0</TotalAmt>
      </CompDisqualPersonsGrp>
      <OtherSalariesAndWagesGrp>
        <TotalAmt>0</TotalAmt>
      </OtherSalariesAndWagesGrp>
      <PensionPlanContributionsGrp>
        <TotalAmt>0</TotalAmt>
      </PensionPlanContributionsGrp>
      <OtherEmployeeBenefitsGrp>
        <TotalAmt>0</TotalAmt>
      </OtherEmployeeBenefitsGrp>
      <PayrollTaxesGrp>
        <TotalAmt>0</TotalAmt>
      </PayrollTaxesGrp>
      <FeesForServicesManagementGrp>
        <TotalAmt>0</TotalAmt>
      </FeesForServicesManagementGrp>
      <FeesForServicesLegalGrp>
        <TotalAmt>0</TotalAmt>
      </FeesForServicesLegalGrp>
      <FeesForServicesAccountingGrp>
        <TotalAmt>950</TotalAmt>
        <ManagementAndGeneralAmt>950</ManagementAndGeneralAmt>
      </FeesForServicesAccountingGrp>
      <FeesForServicesLobbyingGrp>
        <TotalAmt>0</TotalAmt>
      </FeesForServicesLobbyingGrp>
      <FeesForServicesProfFundraising>
        <TotalAmt>0</TotalAmt>
      </FeesForServicesProfFundraising>
      <FeesForSrvcInvstMgmntFeesGrp>
        <TotalAmt>0</TotalAmt>
      </FeesForSrvcInvstMgmntFeesGrp>
      <FeesForServicesOtherGrp>
        <TotalAmt>0</TotalAmt>
      </FeesForServicesOtherGrp>
      <AdvertisingGrp>
        <TotalAmt>0</TotalAmt>
      </AdvertisingGrp>
      <OfficeExpensesGrp>
        <TotalAmt>0</TotalAmt>
      </OfficeExpensesGrp>
      <InformationTechnologyGrp>
        <TotalAmt>0</TotalAmt>
      </InformationTechnologyGrp>
      <RoyaltiesGrp>
        <TotalAmt>0</TotalAmt>
      </RoyaltiesGrp>
      <OccupancyGrp>
        <TotalAmt>0</TotalAmt>
      </OccupancyGrp>
      <TravelGrp>
        <TotalAmt>0</TotalAmt>
      </TravelGrp>
      <PymtTravelEntrtnmntPubOfclGrp>
        <TotalAmt>0</TotalAmt>
      </PymtTravelEntrtnmntPubOfclGrp>
      <ConferencesMeetingsGrp>
        <TotalAmt>0</TotalAmt>
      </ConferencesMeetingsGrp>
      <InterestGrp>
        <TotalAmt>0</TotalAmt>
      </InterestGrp>
      <PaymentsToAffiliatesGrp>
        <TotalAmt>0</TotalAmt>
      </PaymentsToAffiliatesGrp>
      <DepreciationDepletionGrp>
        <TotalAmt>2873</TotalAmt>
        <ProgramServicesAmt>2873</ProgramServicesAmt>
      </DepreciationDepletionGrp>
      <InsuranceGrp>
        <TotalAmt>3225</TotalAmt>
        <ManagementAndGeneralAmt>3225</ManagementAndGeneralAmt>
      </InsuranceGrp>
      <OtherExpensesGrp>
        <Desc>Training</Desc>
        <TotalAmt>153223</TotalAmt>
        <ProgramServicesAmt>153223</ProgramServicesAmt>
      </OtherExpensesGrp>
      <OtherExpensesGrp>
        <Desc>Coaches/Trainers/Referees</Desc>
        <TotalAmt>137339</TotalAmt>
        <ProgramServicesAmt>137339</ProgramServicesAmt>
      </OtherExpensesGrp>
      <OtherExpensesGrp>
        <Desc>Registration Fees</Desc>
        <TotalAmt>39480</TotalAmt>
        <ProgramServicesAmt>39480</ProgramServicesAmt>
      </OtherExpensesGrp>
      <OtherExpensesGrp>
        <Desc>Field Rental</Desc>
        <TotalAmt>18340</TotalAmt>
        <ProgramServicesAmt>18340</ProgramServicesAmt>
      </OtherExpensesGrp>
      <AllOtherExpensesGrp>
        <TotalAmt>42279</TotalAmt>
        <ProgramServicesAmt>24322</ProgramServicesAmt>
        <ManagementAndGeneralAmt>17957</ManagementAndGeneralAmt>
      </AllOtherExpensesGrp>
      <TotalFunctionalExpensesGrp>
        <TotalAmt>414709</TotalAmt>
        <ProgramServicesAmt>392577</ProgramServicesAmt>
        <ManagementAndGeneralAmt>22132</ManagementAndGeneralAmt>
        <FundraisingAmt>0</FundraisingAmt>
      </TotalFunctionalExpensesGrp>
      <CashNonInterestBearingGrp>
        <BOYAmt>234218</BOYAmt>
        <EOYAmt>161291</EOYAmt>
      </CashNonInterestBearingGrp>
      <SavingsAndTempCashInvstGrp>
        <EOYAmt>0</EOYAmt>
      </SavingsAndTempCashInvstGrp>
      <PledgesAndGrantsReceivableGrp>
        <EOYAmt>0</EOYAmt>
      </PledgesAndGrantsReceivableGrp>
      <AccountsReceivableGrp>
        <EOYAmt>0</EOYAmt>
      </AccountsReceivableGrp>
      <ReceivablesFromOfficersEtcGrp>
        <EOYAmt>0</EOYAmt>
      </ReceivablesFromOfficersEtcGrp>
      <RcvblFromDisqualifiedPrsnGrp>
        <EOYAmt>0</EOYAmt>
      </RcvblFromDisqualifiedPrsnGrp>
      <OthNotesLoansReceivableNetGrp>
        <EOYAmt>0</EOYAmt>
      </OthNotesLoansReceivableNetGrp>
      <InventoriesForSaleOrUseGrp>
        <EOYAmt>0</EOYAmt>
      </InventoriesForSaleOrUseGrp>
      <PrepaidExpensesDefrdChargesGrp>
        <EOYAmt>0</EOYAmt>
      </PrepaidExpensesDefrdChargesGrp>
      <LandBldgEquipCostOrOtherBssAmt>11732</LandBldgEquipCostOrOtherBssAmt>
      <LandBldgEquipAccumDeprecAmt>4549</LandBldgEquipAccumDeprecAmt>
      <LandBldgEquipBasisNetGrp>
        <BOYAmt>10056</BOYAmt>
        <EOYAmt>7183</EOYAmt>
      </LandBldgEquipBasisNetGrp>
      <InvestmentsPubTradedSecGrp>
        <EOYAmt>0</EOYAmt>
      </InvestmentsPubTradedSecGrp>
      <InvestmentsOtherSecuritiesGrp>
        <EOYAmt>0</EOYAmt>
      </InvestmentsOtherSecuritiesGrp>
      <InvestmentsProgramRelatedGrp>
        <EOYAmt>0</EOYAmt>
      </InvestmentsProgramRelatedGrp>
      <IntangibleAssetsGrp>
        <EOYAmt>0</EOYAmt>
      </IntangibleAssetsGrp>
      <OtherAssetsTotalGrp>
        <EOYAmt>0</EOYAmt>
      </OtherAssetsTotalGrp>
      <TotalAssetsGrp>
        <BOYAmt>244274</BOYAmt>
        <EOYAmt>168474</EOYAmt>
      </TotalAssetsGrp>
      <TotalLiabilitiesGrp>
        <BOYAmt>0</BOYAmt>
        <EOYAmt>0</EOYAmt>
      </TotalLiabilitiesGrp>
      <OrganizationFollowsSFAS117Ind>X</OrganizationFollowsSFAS117Ind>
      <UnrestrictedNetAssetsGrp>
        <BOYAmt>237974</BOYAmt>
        <EOYAmt>162174</EOYAmt>
      </UnrestrictedNetAssetsGrp>
      <PermanentlyRstrNetAssetsGrp>
        <BOYAmt>6300</BOYAmt>
        <EOYAmt>6300</EOYAmt>
      </PermanentlyRstrNetAssetsGrp>
      <TotalNetAssetsFundBalanceGrp>
        <BOYAmt>244274</BOYAmt>
        <EOYAmt>168474</EOYAmt>
      </TotalNetAssetsFundBalanceGrp>
      <TotLiabNetAssetsFundBalanceGrp>
        <BOYAmt>244274</BOYAmt>
        <EOYAmt>168474</EOYAmt>
      </TotLiabNetAssetsFundBalanceGrp>
      <ReconcilationRevenueExpnssAmt>-75800</ReconcilationRevenueExpnssAmt>
      <MethodOfAccountingAccrualInd>X</MethodOfAccountingAccrualInd>
      <AccountantCompileOrReviewInd>false</AccountantCompileOrReviewInd>
      <FSAuditedInd>false</FSAuditedInd>
      <FederalGrantAuditRequiredInd>false</FederalGrantAuditRequiredInd>
    </IRS990>
    <IRS990ScheduleA documentId="IRS990ScheduleA" softwareId="17005038" softwareVersionNum="2017v2.2">
      <PubliclySupportedOrg509a2Ind>X</PubliclySupportedOrg509a2Ind>
      <GiftsGrantsContrisRcvd509Grp>
        <CurrentTaxYearMinus4YearsAmt>195523</CurrentTaxYearMinus4YearsAmt>
        <CurrentTaxYearMinus3YearsAmt>188109</CurrentTaxYearMinus3YearsAmt>
        <CurrentTaxYearMinus2YearsAmt>249792</CurrentTaxYearMinus2YearsAmt>
        <CurrentTaxYearMinus1YearAmt>310792</CurrentTaxYearMinus1YearAmt>
        <CurrentTaxYearAmt>316643</CurrentTaxYearAmt>
        <TotalAmt>1260859</TotalAmt>
      </GiftsGrantsContrisRcvd509Grp>
      <GrossReceiptsAdmissionsGrp>
        <TotalAmt>0</TotalAmt>
      </GrossReceiptsAdmissionsGrp>
      <GrossReceiptsNonUnrltBusGrp>
        <TotalAmt>0</TotalAmt>
      </GrossReceiptsNonUnrltBusGrp>
      <TaxRevLeviedOrgnztnlBnft509Grp>
        <TotalAmt>0</TotalAmt>
      </TaxRevLeviedOrgnztnlBnft509Grp>
      <GovtFurnSrvcFcltsVl509Grp>
        <TotalAmt>0</TotalAmt>
      </GovtFurnSrvcFcltsVl509Grp>
      <Total509Grp>
        <CurrentTaxYearMinus4YearsAmt>195523</CurrentTaxYearMinus4YearsAmt>
        <CurrentTaxYearMinus3YearsAmt>188109</CurrentTaxYearMinus3YearsAmt>
        <CurrentTaxYearMinus2YearsAmt>249792</CurrentTaxYearMinus2YearsAmt>
        <CurrentTaxYearMinus1YearAmt>310792</CurrentTaxYearMinus1YearAmt>
        <CurrentTaxYearAmt>316643</CurrentTaxYearAmt>
        <TotalAmt>1260859</TotalAmt>
      </Total509Grp>
      <AmountsRcvdDsqlfyPersonGrp>
        <TotalAmt>0</TotalAmt>
      </AmountsRcvdDsqlfyPersonGrp>
      <SubstantialContributorsAmtGrp>
        <TotalAmt>0</TotalAmt>
      </SubstantialContributorsAmtGrp>
      <PublicSupportTotal509Amt>1260859</PublicSupportTotal509Amt>
      <GrossInvestmentIncome509Grp>
        <CurrentTaxYearMinus4YearsAmt>100</CurrentTaxYearMinus4YearsAmt>
        <CurrentTaxYearMinus3YearsAmt>126</CurrentTaxYearMinus3YearsAmt>
        <CurrentTaxYearMinus2YearsAmt>147</CurrentTaxYearMinus2YearsAmt>
        <CurrentTaxYearMinus1YearAmt>145</CurrentTaxYearMinus1YearAmt>
        <CurrentTaxYearAmt>130</CurrentTaxYearAmt>
        <TotalAmt>648</TotalAmt>
      </GrossInvestmentIncome509Grp>
      <Post1975UBTIGrp>
        <TotalAmt>0</TotalAmt>
      </Post1975UBTIGrp>
      <InvestmentIncomeAndUBTIGrp>
        <CurrentTaxYearMinus4YearsAmt>100</CurrentTaxYearMinus4YearsAmt>
        <CurrentTaxYearMinus3YearsAmt>126</CurrentTaxYearMinus3YearsAmt>
        <CurrentTaxYearMinus2YearsAmt>147</CurrentTaxYearMinus2YearsAmt>
        <CurrentTaxYearMinus1YearAmt>145</CurrentTaxYearMinus1YearAmt>
        <CurrentTaxYearAmt>130</CurrentTaxYearAmt>
        <TotalAmt>648</TotalAmt>
      </InvestmentIncomeAndUBTIGrp>
      <NetIncomeFromOtherUBIGrp>
        <TotalAmt>0</TotalAmt>
      </NetIncomeFromOtherUBIGrp>
      <OtherIncome509Grp>
        <TotalAmt>0</TotalAmt>
      </OtherIncome509Grp>
      <TotalSupportCalendarYearGrp>
        <CurrentTaxYearMinus4YearsAmt>195623</CurrentTaxYearMinus4YearsAmt>
        <CurrentTaxYearMinus3YearsAmt>188235</CurrentTaxYearMinus3YearsAmt>
        <CurrentTaxYearMinus2YearsAmt>249939</CurrentTaxYearMinus2YearsAmt>
        <CurrentTaxYearMinus1YearAmt>310937</CurrentTaxYearMinus1YearAmt>
        <CurrentTaxYearAmt>316773</CurrentTaxYearAmt>
        <TotalAmt>1261507</TotalAmt>
      </TotalSupportCalendarYearGrp>
      <PublicSupportCY509Pct>0.99950</PublicSupportCY509Pct>
      <PublicSupportPY509Pct>0.99940</PublicSupportPY509Pct>
      <InvestmentIncomeCYPct>0.00050</InvestmentIncomeCYPct>
      <InvestmentIncomePYPct>0.00060</InvestmentIncomePYPct>
      <ThirtyThrPctSuprtTestsCY509Ind>X</ThirtyThrPctSuprtTestsCY509Ind>
    </IRS990ScheduleA>
    <IRS990ScheduleD documentId="IRS990ScheduleD" softwareId="17005038" softwareVersionNum="2017v2.2">
      <EquipmentGrp>
        <OtherCostOrOtherBasisAmt>11732</OtherCostOrOtherBasisAmt>
        <DepreciationAmt>4549</DepreciationAmt>
        <BookValueAmt>7183</BookValueAmt>
      </EquipmentGrp>
      <TotalBookValueLandBuildingsAmt>7183</TotalBookValueLandBuildingsAmt>
    </IRS990ScheduleD>
    <IRS990ScheduleI documentId="IRS990ScheduleI" softwareId="17005038" softwareVersionNum="2017v2.2">
      <GrantRecordsMaintainedInd>false</GrantRecordsMaintainedInd>
      <RecipientTable>
        <RecipientBusinessName>
          <BusinessNameLine1Txt>HARRISON CENTRAL SCHOOL DISTR</BusinessNameLine1Txt>
        </RecipientBusinessName>
        <USAddress>
          <AddressLine1Txt>50 UNION AVENUE</AddressLine1Txt>
          <CityNm>HARRISON</CityNm>
          <StateAbbreviationCd>NY</StateAbbreviationCd>
          <ZIPCd>10528</ZIPCd>
        </USAddress>
        <CashGrantAmt>17000</CashGrantAmt>
        <NonCashAssistanceAmt>0</NonCashAssistanceAmt>
      </RecipientTable>
      <Total501c3OrgCnt>1</Total501c3OrgCnt>
      <TotalOtherOrgCnt>0</TotalOtherOrgCnt>
    </IRS990ScheduleI>
    <IRS990ScheduleO documentId="IRS990ScheduleO" softwareId="17005038" softwareVersionNum="2017v2.2">
      <SupplementalInformationDetail>
        <FormAndLineReferenceDesc>Form 990, Part VI, Line 11b: Form 990 Review Process</FormAndLineReferenceDesc>
        <ExplanationTxt>No review was or will be conducted.</ExplanationTxt>
      </SupplementalInformationDetail>
      <SupplementalInformationDetail>
        <FormAndLineReferenceDesc>Form 990, Part VI, Line 19: Other Organization Documents Publicly Available</FormAndLineReferenceDesc>
        <ExplanationTxt>No documents available to the public.</ExplanationTxt>
      </SupplementalInformationDetail>
      <SupplementalInformationDetail>
        <FormAndLineReferenceDesc>Form 990, Part IX, Line 24e: Other Expenses</FormAndLineReferenceDesc>
        <ExplanationTxt>Bank charges: Column (A) - Total = $414; Column (B) - Program Services = $0; Column (C) - Management &amp; General = $414; Column (D) - Fundraising = $0</ExplanationTxt>
      </SupplementalInformationDetail>
      <SupplementalInformationDetail>
        <FormAndLineReferenceDesc>Form 990, Part IX, Line 24e: Other Expenses</FormAndLineReferenceDesc>
        <ExplanationTxt>Credit card processing fees: Column (A) - Total = $14137; Column (B) - Program Services = $0; Column (C) - Management &amp; General = $14137; Column (D) - Fundraising = $0</ExplanationTxt>
      </SupplementalInformationDetail>
      <SupplementalInformationDetail>
        <FormAndLineReferenceDesc>Form 990, Part IX, Line 24e: Other Expenses</FormAndLineReferenceDesc>
        <ExplanationTxt>Equipment &amp; Supplies: Column (A) - Total = $9829; Column (B) - Program Services = $9829; Column (C) - Management &amp; General = $0; Column (D) - Fundraising = $0</ExplanationTxt>
      </SupplementalInformationDetail>
      <SupplementalInformationDetail>
        <FormAndLineReferenceDesc>Form 990, Part IX, Line 24e: Other Expenses</FormAndLineReferenceDesc>
        <ExplanationTxt>Licenses &amp; permits: Column (A) - Total = $0; Column (B) - Program Services = $0; Column (C) - Management &amp; General = $0; Column (D) - Fundraising = $0</ExplanationTxt>
      </SupplementalInformationDetail>
      <SupplementalInformationDetail>
        <FormAndLineReferenceDesc>Form 990, Part IX, Line 24e: Other Expenses</FormAndLineReferenceDesc>
        <ExplanationTxt>Meeting expense: Column (A) - Total = $3272; Column (B) - Program Services = $0; Column (C) - Management &amp; General = $3272; Column (D) - Fundraising = $0</ExplanationTxt>
      </SupplementalInformationDetail>
      <SupplementalInformationDetail>
        <FormAndLineReferenceDesc>Form 990, Part IX, Line 24e: Other Expenses</FormAndLineReferenceDesc>
        <ExplanationTxt>Postage and Shipping: Column (A) - Total = $134; Column (B) - Program Services = $0; Column (C) - Management &amp; General = $134; Column (D) - Fundraising = $0</ExplanationTxt>
      </SupplementalInformationDetail>
      <SupplementalInformationDetail>
        <FormAndLineReferenceDesc>Form 990, Part IX, Line 24e: Other Expenses</FormAndLineReferenceDesc>
        <ExplanationTxt>Printing and Publications: Column (A) - Total = $1819; Column (B) - Program Services = $1819; Column (C) - Management &amp; General = $0; Column (D) - Fundraising = $0</ExplanationTxt>
      </SupplementalInformationDetail>
      <SupplementalInformationDetail>
        <FormAndLineReferenceDesc>Form 990, Part IX, Line 24e: Other Expenses</FormAndLineReferenceDesc>
        <ExplanationTxt>Scholarship &amp; Contributions: Column (A) - Total = $2000; Column (B) - Program Services = $2000; Column (C) - Management &amp; General = $0; Column (D) - Fundraising = $0</ExplanationTxt>
      </SupplementalInformationDetail>
      <SupplementalInformationDetail>
        <FormAndLineReferenceDesc>Form 990, Part IX, Line 24e: Other Expenses</FormAndLineReferenceDesc>
        <ExplanationTxt>Tournament expenses: Column (A) - Total = $3045; Column (B) - Program Services = $3045; Column (C) - Management &amp; General = $0; Column (D) - Fundraising = $0</ExplanationTxt>
      </SupplementalInformationDetail>
      <SupplementalInformationDetail>
        <FormAndLineReferenceDesc>Form 990, Part IX, Line 24e: Other Expenses</FormAndLineReferenceDesc>
        <ExplanationTxt>Uniforms: Column (A) - Total = $7629; Column (B) - Program Services = $7629; Column (C) - Management &amp; General = $0; Column (D) - Fundraising = $0</ExplanationTxt>
      </SupplementalInformationDetail>
    </IRS990ScheduleO>
  </ReturnData>
</Return>